setup.py
wayround_org/webserver/__init__.py
wayround_org/webserver/application.py
wayround_org/webserver/commands.py
wayround_org/webserver/config.py
wayround_org/webserver/main.py
wayround_org/webserver/module_miscs.py
wayround_org/webserver/server.py
wayround_org/webserver/socket.py
wayround_org/webserver/modules/proxy.py
wayround_org/webserver/modules/proxy_ah_php.py
wayround_org/webserver/modules/wsgi.py
wayround_org_webserver.egg-info/PKG-INFO
wayround_org_webserver.egg-info/SOURCES.txt
wayround_org_webserver.egg-info/dependency_links.txt
wayround_org_webserver.egg-info/entry_points.txt
wayround_org_webserver.egg-info/requires.txt
wayround_org_webserver.egg-info/top_level.txt