Metadata-Version: 1.1
Name: wayround-org-webserver
Version: 0.2.5
Summary: homebrewn webserver
Home-page: https://github.com/AnimusPEXUS/wayround_org_webserver
Author: Alexey Gorshkov
Author-email: animus@wayround.org
License: UNKNOWN
Platform: UNKNOWN
Classifier: License :: OSI Approved :: GNU General Public License v3 or later (GPLv3+)
